{
  "teachers": [
    {
      "id": 2,
      "name": "圆圆的海峰",
      "age": 19
    },
    {
      "id": 3,
      "name": "渊哥",
      "age": 20
    },
    {
      "id": 4,
      "name": "强",
      "age": 21
    },
    {
      "name": "志勇老师",
      "age": "18",
      "id": 5
    }
  ],
  "students": [
    {
      "id": 1,
      "name": "佩奇",
      "age": 18
    },
    {
      "id": 2,
      "name": "乔治",
      "age": 19
    }
  ],
  "school": {
    "name": "atguigu"
  }
}